st_modal/__init__.py
st_modal-1.0.2.dist-info/licenses/LICENSE
st_modal-1.0.2.dist-info/METADATA
st_modal-1.0.2.dist-info/WHEEL
st_modal-1.0.2.dist-info/top_level.txt
st_modal-1.0.2.dist-info/RECORD
