Metadata-Version: 2.4
Name: st-modal
Version: 1.0.2
Summary: Modal for streamlit
Author: Peter van Lunteren
License: BSD
Project-URL: Homepage, https://github.com/PetervanLunteren/st-modal
Project-URL: Repository, https://github.com/PetervanLunteren/st-modal
Project-URL: Issues, https://github.com/PetervanLunteren/st-modal/issues
Keywords: streamlit,modal,dialog,ui,component
Classifier: Intended Audience :: Developers
Classifier: Intended Audience :: Science/Research
Classifier: Programming Language :: Python :: 3
Classifier: Programming Language :: Python :: 3.7
Classifier: Programming Language :: Python :: 3.8
Classifier: Programming Language :: Python :: 3.9
Classifier: Programming Language :: Python :: 3.10
Classifier: Programming Language :: Python :: 3.11
Classifier: Programming Language :: Python :: 3.12
Classifier: License :: OSI Approved :: BSD License
Classifier: Topic :: Scientific/Engineering
Classifier: Development Status :: 4 - Beta
Requires-Python: >=3.7
License-File: LICENSE
Requires-Dist: streamlit
Requires-Dist: deprecation
Dynamic: license-file
